MANIFEST.in
README.rst
requirements.txt
setup.cfg
setup.py
/Users/mikaelmortensen/MySoftware/mpiFFT4py/mpiFFT4py/cython/maths.pyx
mpiFFT4py/__init__.py
mpiFFT4py/line.py
mpiFFT4py/mpibase.py
mpiFFT4py/pencil.py
mpiFFT4py/slab.py
mpiFFT4py.egg-info/PKG-INFO
mpiFFT4py.egg-info/SOURCES.txt
mpiFFT4py.egg-info/dependency_links.txt
mpiFFT4py.egg-info/requires.txt
mpiFFT4py.egg-info/top_level.txt
mpiFFT4py/cython/__init__.py
mpiFFT4py/cython/maths.pyx
mpiFFT4py/serialFFT/__init__.py
mpiFFT4py/serialFFT/numpy_fft.py
mpiFFT4py/serialFFT/pyfftw_fft.py