Metadata-Version: 1.1
Name: mpiFFT4py
Version: 1.1.2
Summary: mpiFFT4py -- Parallel 3D FFT in Python using MPI for Python
Home-page: https://github.com/spectralDNS/mpiFFT4py
Author: Mikael Mortensen
Author-email: mikaem@math.uio.no
License: UNKNOWN
Platform: UNKNOWN
Classifier: Development Status :: 5 - Production/Stable
Classifier: Environment :: Console
Classifier: Intended Audience :: Developers
Classifier: Intended Audience :: Science/Research
Classifier: Intended Audience :: Education
Classifier: Programming Language :: Python
Classifier: Programming Language :: Python :: 2
Classifier: Programming Language :: Python :: 3
Classifier: License :: OSI Approved :: GNU Library or Lesser General Public License (LGPL)
Classifier: Topic :: Scientific/Engineering :: Mathematics
Classifier: Topic :: Software Development :: Libraries :: Python Modules
